dataform_view_migrator/__init__.py
dataform_view_migrator/__main__.py
dataform_view_migrator/bq.py
dataform_view_migrator/cli.py
dataform_view_migrator/config.py
dataform_view_migrator/migrate.py
dataform_view_migrator-0.1.6.dist-info/METADATA
dataform_view_migrator-0.1.6.dist-info/WHEEL
dataform_view_migrator-0.1.6.dist-info/entry_points.txt
dataform_view_migrator-0.1.6.dist-info/licenses/LICENSE
dataform_view_migrator-0.1.6.dist-info/RECORD
