Metadata-Version: 2.4
Name: dataform-view-migrator
Version: 0.1.6
Summary: Migrate BigQuery views into Dataform view definitions.
Author: Alan Vainsencher
License: MIT
License-File: LICENSE
Keywords: bigquery,bigquery-views,dataform
Classifier: Programming Language :: Python :: 3
Classifier: Programming Language :: Python :: 3 :: Only
Classifier: Programming Language :: Python :: 3.10
Classifier: Programming Language :: Python :: 3.11
Classifier: Programming Language :: Python :: 3.12
Requires-Python: >=3.10
Requires-Dist: google-cloud-bigquery>=3.25.0
Requires-Dist: polars>=1.12.0
Requires-Dist: tomli>=2.0.1; python_version < '3.11'
Requires-Dist: typer>=0.12.0
